Metadata-Version: 2.1
Name: julia-client-chatting
Version: 0.0.1
Summary: Mess Client
Home-page: UNKNOWN
Author: Zakharova Julia
Author-email: sorulai@yandex.ru
License: UNKNOWN
Platform: UNKNOWN
Requires-Dist: PyQt5
Requires-Dist: sqlalchemy
Requires-Dist: pycryptodome
Requires-Dist: pycryptodomex
